{"type":"FeatureCollection","features":[{"type":"Feature","properties":{"name:sr":"22221 Лаћарак","opening_hours":"Mo-Fr 08:00-14:00; Sa 08:00-12:00; PH off","addr:housenumber":"245","name":"22221 Лаћарак","amenity":"post_office","phone":"+381 22 600-679","ref":"22221","name:sr-Latn":"22221 Laćarak","addr:pak":"322494","addr:street":"Првог новембра"},"geometry":{"type":"Point","coordinates":[19.5635687534863,44.9981218569746]}},{"type":"Feature","properties":{"name:sr":"22103 Сремска Митровица","opening_hours":"Mo-Fr 07:00-13:00; Sa 08:00-12:00; PH off","addr:housenumber":"25","name":"22103 Сремска Митровица","amenity":"post_office","phone":"+381 22 626589","ref":"22103","name:sr-Latn":"22103 Sremska Mitrovica","addr:pak":"320107","addr:street":"Стари мост"},"geometry":{"type":"Point","coordinates":[19.5941906683335,44.9755997242883]}}]}