{"type":"FeatureCollection","features":[{"type":"Feature","properties":{"name:sr":"15355 Црна Бара","opening_hours":"Mo-Fr 08:00-14:00; PH off","addr:housenumber":"2","name":"15355 Црна Бара","amenity":"post_office","phone":"+381 15 438-001","ref":"15355","name:sr-Latn":"15355 Crna Bara","addr:pak":"277021","addr:street":"Мике Митровића"},"geometry":{"type":"Point","coordinates":[19.3945142874516,44.8701699486298]}}]}