{"type":"FeatureCollection","features":[{"type":"Feature","properties":{"name:sr":"15308 Јадранска Лешница","opening_hours":"Mo-Fr 08:00-13:30; PH off","addr:housenumber":"1","name":"15308 Јадранска Лешница","amenity":"post_office","phone":"+381 15 852-017","ref":"15308","name:sr-Latn":"15308 Jadranska Lešnica","addr:pak":"263606","addr:street":"Војводе Мишића"},"geometry":{"type":"Point","coordinates":[19.3486877278841,44.5858465811545]}},{"type":"Feature","properties":{"name:sr":"15309 Брезјак","opening_hours":"Mo-Fr 08:00-14:00; PH off","addr:housenumber":"2","name":"15309 Брезјак","amenity":"post_office","phone":"+381 15 843-488","ref":"15309","name:sr-Latn":"15309 Brezjak","addr:pak":"263215","addr:street":"Стевана Синђелића"},"geometry":{"type":"Point","coordinates":[19.3420450402426,44.5100844661258]}},{"type":"Feature","properties":{"amenity":"post_office","name":"15311 Драгинац","name:sr":"15311 Драгинац","name:sr-Latn":"15311 Draginac","ref":"15311","opening_hours":"Mo-Sa 08:00-13:30; PH off","phone":"+381 15 854-797","addr:pak":"263311"},"geometry":{"type":"Point","coordinates":[19.4169917966382,44.5095843345889]}}]}