{"type":"FeatureCollection","features":[{"type":"Feature","properties":{"name:sr":"11507 Стублине","opening_hours":"Mo-Fr 08:00-14:00; PH off","addr:housenumber":"507А","name":"11507 Стублине","amenity":"post_office","phone":"+381 11 8791-188","ref":"11507","name:sr-Latn":"11507 Stubline","addr:pak":"211607","addr:street":"Црноборска"},"geometry":{"type":"Point","coordinates":[20.15073394958,44.5706251998614]}},{"type":"Feature","properties":{"amenity":"post_office","name":"14212 Бргуле","name:sr":"14212 Бргуле","name:sr-Latn":"14212 Brgule","ref":"14212","opening_hours":"Mo-Fr 07:00-14:00; PH off","phone":"+381 14 3473-100","addr:pak":"241701"},"geometry":{"type":"Point","coordinates":[20.2049269813922,44.5176259582953]}}]}