{"type":"FeatureCollection","features":[{"type":"Feature","properties":{"name:sr":"11562 Јунковац","opening_hours":"Mo-Fr 08:00-14:00; PH off","addr:housenumber":"ББ","name":"11562 Јунковац","amenity":"post_office","phone":"+381 11 8177-131","ref":"11562","name:sr-Latn":"11562 Junkovac","addr:pak":"217302","addr:street":"Трг ослобођења"},"geometry":{"type":"Point","coordinates":[20.3517975337808,44.4494101372633]}}]}