{"type":"FeatureCollection","features":[{"type":"Feature","properties":{"name:sr":"11460 Барајево","opening_hours":"Mo-Fr 08:00-19:00; Sa 08:00-14:00; PH off","addr:housenumber":"4","name":"11460 Барајево","amenity":"post_office","phone":"+381 11 3535-147;+381 11 3535-150","ref":"11460","name:sr-Latn":"11460 Barajevo","addr:pak":"218103","addr:street":"Светосавска"},"geometry":{"type":"Point","coordinates":[20.4160673164358,44.5782459748793]}}]}