{"type":"FeatureCollection","features":[{"type":"Feature","properties":{"name:sr":"19250 Мајданпек","opening_hours":"Mo-Fr 07:00-19:00; Sa 08:00-13:00; PH off","addr:housenumber":"44","name":"19250 Мајданпек","amenity":"post_office","phone":"+381 30 453-331;+381 30 581-643","ref":"19250","name:sr-Latn":"19250 Majdanpek","addr:pak":"605002","addr:street":"Капетанска"},"geometry":{"type":"Point","coordinates":[21.9408926231976,44.4250114694462]}}]}