{"type":"FeatureCollection","features":[{"type":"Feature","properties":{"name:sr":"19220 Доњи Милановац","opening_hours":"Mo-Fr 08:00-16:00; Sa 08:00-13:00; PH off","addr:housenumber":"4А","name":"19220 Доњи Милановац","amenity":"post_office","phone":"+381 30 453-330;+381 30 590-893","ref":"19220","name:sr-Latn":"19220 Donji Milanovac","addr:pak":"606003","addr:street":"Краља Петра првог"},"geometry":{"type":"Point","coordinates":[22.1522570791204,44.4667330991511]}}]}