{"type":"FeatureCollection","features":[{"type":"Feature","properties":{"name:sr":"19321 Подвршка","opening_hours":"Mo 11:00-13:00; Mo 07:00-10:00; We 11:00-13:00; We 07:00-10:00; Fr 11:00-13:00; Fr 07:00-10:00; PH off","addr:housenumber":"1","name":"19321 Подвршка","amenity":"post_office","phone":"+381 19 806-001","ref":"19321","name:sr-Latn":"19321 Podvrška","addr:pak":"619318","addr:street":"Маршала Тита"},"geometry":{"type":"Point","coordinates":[22.4966663919963,44.5851627892612]}},{"type":"Feature","properties":{"name:sr":"19323 Брза Паланка","opening_hours":"Mo-Fr 07:30-14:30; PH off","addr:housenumber":"А4","name":"19323 Брза Паланка","amenity":"post_office","phone":"+381 19 85-327","ref":"19323","name:sr-Latn":"19323 Brza Palanka","addr:pak":"619450","addr:street":"Трг републике"},"geometry":{"type":"Point","coordinates":[22.4540397670804,44.4827085229677]}},{"type":"Feature","properties":{"name:sr":"19327 Грабовица","opening_hours":"Mo,We,Fr 08:00-11:00; PH off","addr:housenumber":"ББ","name":"19327 Грабовица","amenity":"post_office","phone":"+381 19 3885-913","ref":"19327","name:sr-Latn":"19327 Grabovica","addr:pak":"619966","addr:street":"Маршала Тита"},"geometry":{"type":"Point","coordinates":[22.490244092609,44.4947677154118]}}]}