{"type":"FeatureCollection","features":[{"type":"Feature","properties":{"name:sr":"21203 Ветерник","opening_hours":"Mo-Fr 08:00-19:00; Sa 08:00-13:00; PH off","addr:housenumber":"8","name":"21203 Ветерник","amenity":"post_office","phone":"+381 21 4807-092;+381 21 821-003","ref":"21203","name:sr-Latn":"21203 Veternik","addr:pak":"407556","addr:street":"Омладинска"},"geometry":{"type":"Point","coordinates":[19.7540836405591,45.2505159833433]}},{"type":"Feature","properties":{"name:sr":"21410 Футог","opening_hours":"Mo-Fr 08:00-19:00; Sa 08:00-13:00; PH off","addr:housenumber":"19","name":"21410 Футог","amenity":"post_office","phone":"+381 21 4807-085;+381 21 895-951","ref":"21410","name:sr-Latn":"21410 Futog","addr:pak":"408426","addr:street":"Цара Лазара"},"geometry":{"type":"Point","coordinates":[19.7039249672379,45.2379799522476]}},{"type":"Feature","properties":{"name:sr":"21409 Футог","opening_hours":"Mo-Fr 08:00-15:00; PH off","addr:housenumber":"52","name":"21409 Футог","amenity":"post_office","phone":"+381 21 897-419","ref":"21409","name:sr-Latn":"21409 Futog","addr:pak":"408219","addr:street":"Симе Шолаје"},"geometry":{"type":"Point","coordinates":[19.6902842081389,45.2416249187403]}},{"type":"Feature","properties":{"name:sr":"21408 Футог","opening_hours":"Mo-Sa 07:30-19:30; Su 07:00-13:00; PH 07:30-19:30","addr:housenumber":"44","name":"21408 Футог","amenity":"post_office","phone":"+381 21 895-776","ref":"21408","name:sr-Latn":"21408 Futog","addr:pak":"408464","addr:street":"Раде Кондића"},"geometry":{"type":"Point","coordinates":[19.7090286916095,45.2405136619436]}}]}