{"type":"FeatureCollection","features":[{"type":"Feature","properties":{"amenity":"post_office","name":"21103 Нови Сад","name:sr":"21103 Нови Сад","name:sr-Latn":"21103 Novi Sad","ref":"21103","opening_hours":"Mo-Fr 08:00-19:00; Sa 08:00-13:00; PH off","phone":"+381 21 6614-879","addr:pak":"400931"},"geometry":{"type":"Point","coordinates":[19.8344590117228,45.2609010055832]}},{"type":"Feature","properties":{"name:sr":"21130 Нови Сад","opening_hours":"Mo-Su,PH 07:00-20:00","addr:housenumber":"23","name":"21130 Нови Сад","amenity":"post_office","phone":"+381 21 419-510","ref":"21130","name:sr-Latn":"21130 Novi Sad","addr:pak":"400867","addr:street":"Теодора Мандића"},"geometry":{"type":"Point","coordinates":[19.8315189766519,45.2728919693068]}}]}