{"type":"FeatureCollection","features":[{"type":"Feature","properties":{"name:sr":"36342 Ушће","opening_hours":"Mo-Fr 07:30-13:30; PH off","addr:housenumber":"13","name":"36342 Ушће","amenity":"post_office","phone":"+381 36 303-126;+381 36 5430-116","ref":"36342","name:sr-Latn":"36342 Ušće","addr:pak":"565303","addr:street":"Двадесеттрећег новембра"},"geometry":{"type":"Point","coordinates":[20.6181857150334,43.468106221019]}}]}