{"type":"FeatureCollection","features":[{"type":"Feature","properties":{"amenity":"post_office","name":"31207 Сирогојно","name:sr":"31207 Сирогојно","name:sr-Latn":"31207 Sirogojno","ref":"31207","opening_hours":"Mo-Fr 08:00-15:00; PH off","phone":"+381 31 3802-050","addr:pak":"509801"},"geometry":{"type":"Point","coordinates":[19.8796229611659,43.6867885525285]}},{"type":"Feature","properties":{"amenity":"post_office","name":"31234 Бреково","name:sr":"31234 Бреково","name:sr-Latn":"31234 Brekovo","ref":"31234","opening_hours":"Mo,Th 08:00-11:00; PH off","phone":"+381 31 897-145","addr:pak":"506507"},"geometry":{"type":"Point","coordinates":[20.017126292548,43.6400077144755]}}]}