{"type":"FeatureCollection","features":[{"type":"Feature","properties":{"amenity":"post_office","name":"31206 Равни","name:sr":"31206 Равни","name:sr-Latn":"31206 Ravni","ref":"31206","opening_hours":"Mo-Fr 08:00-14:00; PH off","phone":"+381 31 3809-046","addr:pak":"503815"},"geometry":{"type":"Point","coordinates":[19.888240651745,43.7405758520251]}},{"type":"Feature","properties":{"amenity":"post_office","name":"31237 Роге","name:sr":"31237 Роге","name:sr-Latn":"31237 Roge","ref":"31237","opening_hours":"Mo-Fr 08:00-11:00; PH off","phone":"+381 31 820-811","addr:pak":"505701"},"geometry":{"type":"Point","coordinates":[19.9819145103758,43.7760622760429]}}]}