{"type":"FeatureCollection","features":[{"type":"Feature","properties":{"amenity":"post_office","name":"31311 Бела Земља","name:sr":"31311 Бела Земља","name:sr-Latn":"31311 Bela Zemlja","ref":"31311","opening_hours":"Mo-Fr 08:00-15:00; PH off","phone":"+381 31 571-282","addr:pak":"503905"},"geometry":{"type":"Point","coordinates":[19.8023111995237,43.8274571871997]}},{"type":"Feature","properties":{"name:sr":"31312 Мачкат","opening_hours":"Mo-Fr 08:00-15:00; PH off","addr:housenumber":"ББ","name":"31312 Мачкат","amenity":"post_office","phone":"+381 31 3834-099","ref":"31312","name:sr-Latn":"31312 Mačkat","addr:pak":"509701","addr:street":"Мачкат"},"geometry":{"type":"Point","coordinates":[19.7801031467746,43.7913121376954]}}]}