{"type":"FeatureCollection","features":[{"type":"Feature","properties":{"name:sr":"31230 Ариље","opening_hours":"Mo-Fr 08:00-19:00; Sa 08:00-15:00; PH off","addr:housenumber":"35","name":"31230 Ариље","amenity":"post_office","phone":"+381 31 590-859;+381 31 590-860","ref":"31230","name:sr-Latn":"31230 Arilje","addr:pak":"505804","addr:street":"Светог Ахилија"},"geometry":{"type":"Point","coordinates":[20.0993145356714,43.7514293648014]}},{"type":"Feature","properties":{"name:sr":"31212 Пожега","opening_hours":"Mo-Fr 08:00-15:00; Sa 08:00-12:00; PH off","addr:housenumber":"1","name":"31212 Пожега","amenity":"post_office","phone":"+381 31 812-014","ref":"31212","name:sr-Latn":"31212 Požega","addr:pak":"505161","addr:street":"Браће Мићића"},"geometry":{"type":"Point","coordinates":[20.0410820819549,43.8319971090675]}}]}