{"type":"FeatureCollection","features":[{"type":"Feature","properties":{"amenity":"post_office","name":"36205 Роћевићи","name:sr":"36205 Роћевићи","name:sr-Latn":"36205 Roćevići","ref":"36205","opening_hours":"Tu,Th 07:30-14:30; PH off","phone":"+381 36 825-112","addr:pak":"564501"},"geometry":{"type":"Point","coordinates":[20.4975772421075,43.7063295637758]}},{"type":"Feature","properties":{"amenity":"post_office","name":"36341 Богутовац","name:sr":"36341 Богутовац","name:sr-Latn":"36341 Bogutovac","ref":"36341","opening_hours":"Mo-Fr 07:00-14:00; PH off","phone":"+381 36 5826-026","addr:pak":"565201"},"geometry":{"type":"Point","coordinates":[20.5545668349752,43.650697709627]}}]}