{"type":"FeatureCollection","features":[{"type":"Feature","properties":{"name:sr":"32240 Лучани","opening_hours":"Mo-Fr 08:00-15:00; Sa 08:00-13:00; PH off","addr:housenumber":"2В","name":"32240 Лучани","amenity":"post_office","phone":"+381 32 304-077;+381 32 817-154","ref":"32240","name:sr-Latn":"32240 Lučani","addr:pak":"535201","addr:street":"Радничка"},"geometry":{"type":"Point","coordinates":[20.1360439072414,43.85978567041]}},{"type":"Feature","properties":{"amenity":"post_office","name":"32242 Овчар Бања","name:sr":"32242 Овчар Бања","name:sr-Latn":"32242 Ovčar Banja","ref":"32242","opening_hours":"Mo,We,Fr 07:30-11:00; PH off","phone":"+381 32 5596-100","addr:pak":"525921"},"geometry":{"type":"Point","coordinates":[20.1870447208047,43.8996197927219]}},{"type":"Feature","properties":{"amenity":"post_office","name":"31214 Горња Добриња","name:sr":"31214 Горња Добриња","name:sr-Latn":"31214 Gornja Dobrinja","ref":"31214","opening_hours":"Mo-Fr 08:00-11:00; PH off","phone":"+381 31 818-111","addr:pak":"505501"},"geometry":{"type":"Point","coordinates":[20.078704272037,43.9611744952791]}},{"type":"Feature","properties":{"amenity":"post_office","name":"31215 Јелен До","name:sr":"31215 Јелен До","name:sr-Latn":"31215 Jelen Do","ref":"31215","opening_hours":"Mo,Th 08:00-11:00; PH off","phone":"+381 31 3810-511","addr:pak":"505601"},"geometry":{"type":"Point","coordinates":[20.1194355667065,43.8904500419559]}}]}