{"type":"FeatureCollection","features":[{"type":"Feature","properties":{"amenity":"post_office","name":"31203 Луново Село","name:sr":"31203 Луново Село","name:sr-Latn":"31203 Lunovo Selo","ref":"31203","opening_hours":"Mo-Fr 08:00-11:00; PH off","phone":"+381 31 803-780","addr:pak":"503701"},"geometry":{"type":"Point","coordinates":[19.938310274446,43.8817251393709]}},{"type":"Feature","properties":{"name:sr":"31204 Каран","opening_hours":"Mo-Fr 08:00-14:00; PH off","addr:housenumber":"ББ","name":"31204 Каран","amenity":"post_office","phone":"+381 31 803-650","ref":"31204","name:sr-Latn":"31204 Karan","addr:pak":"503601","addr:street":"Краља Александра Карађорђевића"},"geometry":{"type":"Point","coordinates":[19.9105210026944,43.9162728089171]}},{"type":"Feature","properties":{"name:sr":"31205 Севојно","opening_hours":"Mo-Fr 08:00-19:00; Sa 08:00-15:00; PH off","addr:housenumber":"33","name":"31205 Севојно","amenity":"post_office","phone":"+381 31 590-852;+381 31 532-632","ref":"31205","name:sr-Latn":"31205 Sevojno","addr:pak":"503118","addr:street":"Миливоја Марића"},"geometry":{"type":"Point","coordinates":[19.89654063397,43.846346465638]}},{"type":"Feature","properties":{"name:sr":"31210 Пожега","opening_hours":"Mo-Fr 08:00-19:00; Sa 08:00-15:00; PH off","addr:housenumber":"2","name":"31210 Пожега","amenity":"post_office","phone":"+381 31 590-855;+381 31 590-897","ref":"31210","name:sr-Latn":"31210 Požega","addr:pak":"504702","addr:street":"Краља Петра"},"geometry":{"type":"Point","coordinates":[20.0356154515788,43.8465453431626]}}]}