{"type":"FeatureCollection","features":[{"type":"Feature","properties":{"name:sr":"11060 Београд 38","opening_hours":"Mo-Fr 08:00-19:00; Sa 08:00-15:00; PH off","addr:housenumber":"50","name":"11060 Београд 38","amenity":"post_office","phone":"+381 11 2771-095;+381 11 2776-416;+381 11 3210-113","ref":"11060","name:sr-Latn":"11060 Beograd 38","addr:pak":"137413","addr:street":"Патриса Лумумбе"},"geometry":{"type":"Point","coordinates":[20.5121245896625,44.814768257763]}},{"type":"Feature","properties":{"name:sr":"11164 Београд 106","opening_hours":"Mo-Sa 08:00-19:00; Su 08:00-15:00; PH off","addr:housenumber":"18Б","name":"11164 Београд 106","amenity":"post_office","phone":"+381 11 2972-020","ref":"11164","name:sr-Latn":"11164 Beograd 106","addr:pak":"138207","addr:street":"Миријевски булевар"},"geometry":{"type":"Point","coordinates":[20.5223351939227,44.8116219047373]}},{"type":"Feature","properties":{"name:sr":"11062 Београд 150","opening_hours":"Mo-Su,PH 09:00-19:00","addr:housenumber":"84","name":"11062 Београд 150","amenity":"post_office","phone":"+381 64 665-77-94","ref":"11062","name:sr-Latn":"11062 Beograd 150","addr:pak":"138815","addr:street":"Вишњичка"},"geometry":{"type":"Point","coordinates":[20.5082506087344,44.8168666119746]}}]}