{"type":"FeatureCollection","features":[{"type":"Feature","properties":{"name:sr":"11122 Београд 110","opening_hours":"Mo-Fr 08:00-19:00; Sa 08:00-12:00; PH off","addr:housenumber":"2","name":"11122 Београд 110","amenity":"post_office","phone":"+381 11 2758-222;+381 11 2970-028","ref":"11122","name:sr-Latn":"11122 Beograd 110","addr:pak":"139302","addr:street":"Слободана Јовановића"},"geometry":{"type":"Point","coordinates":[20.5362731393962,44.8163982549723]}},{"type":"Feature","properties":{"name:sr":"11145 Београд 41","opening_hours":"Mo-Fr 08:00-15:00; PH off","addr:housenumber":"126","name":"11145 Београд 41","amenity":"post_office","phone":"+381 11 2990-641","ref":"11145","name:sr-Latn":"11145 Beograd 41","addr:pak":"139445","addr:street":"Маршала Тита"},"geometry":{"type":"Point","coordinates":[20.5490173787382,44.8311631911648]}}]}