{"type":"FeatureCollection","features":[{"type":"Feature","properties":{"name:sr":"24417 Мартонош","opening_hours":"Mo-Fr 07:00-14:00; PH off","addr:housenumber":"5","name":"24417 Мартонош","amenity":"post_office","phone":"+381 24 4880-000","ref":"24417","name:sr-Latn":"24417 Martonoš","addr:pak":"445402","addr:street":"Трг Слободе"},"geometry":{"type":"Point","coordinates":[20.059175624474,46.1139997548164]}},{"type":"Feature","properties":{"name:sr":"23333 Мајдан","opening_hours":"Mo,We,Fr 08:00-11:00; PH off","addr:housenumber":"3","name":"23333 Мајдан","amenity":"post_office","phone":"+381 230 88-217","ref":"23333","name:sr-Latn":"23333 Majdan","addr:pak":"375601","addr:street":"Маршала Тита"},"geometry":{"type":"Point","coordinates":[20.2598680505529,46.0943999377007]}},{"type":"Feature","properties":{"name:sr":"23334 Српски Крстур","opening_hours":"Mo-Fr 07:00-11:00; PH off","addr:housenumber":"13","name":"23334 Српски Крстур","amenity":"post_office","phone":"+381 230 387-022","ref":"23334","name:sr-Latn":"23334 Srpski Krstur","addr:pak":"375701","addr:street":"Николе Тесле"},"geometry":{"type":"Point","coordinates":[20.0918761875916,46.1264506631793]}},{"type":"Feature","properties":{"name:sr":"23335 Ђала","opening_hours":"Mo-Fr 07:00-11:00; PH off","addr:housenumber":"12","name":"23335 Ђала","amenity":"post_office","phone":"+381 230 86-111","ref":"23335","name:sr-Latn":"23335 Đala","addr:pak":"375801","addr:street":"Змај Јовина"},"geometry":{"type":"Point","coordinates":[20.1088049063796,46.1549790815479]}}]}