{"type":"FeatureCollection","features":[{"type":"Feature","properties":{"name:sr":"15322 Велика Река","opening_hours":"Mo-Fr 07:00-11:00; PH off","addr:housenumber":"ББ","name":"15322 Велика Река","amenity":"post_office","phone":"+381 15 7464-016","ref":"15322","name:sr-Latn":"15322 Velika Reka","addr:pak":"267315","addr:street":"Краља Петра првог"},"geometry":{"type":"Point","coordinates":[19.2348889328657,44.2669660623669]}}]}