{"type":"FeatureCollection","features":[{"type":"Feature","properties":{"name:sr":"11307 Болеч","opening_hours":"Mo-Fr 08:00-19:00; Sa 08:00-14:00; PH off","addr:housenumber":"78","name":"11307 Болеч","amenity":"post_office","phone":"+381 11 3210-138;+381 11 8063-850","ref":"11307","name:sr-Latn":"11307 Boleč","addr:pak":"154417","addr:street":"Смедеревски пут"},"geometry":{"type":"Point","coordinates":[20.6111687466792,44.7355063261967]}},{"type":"Feature","properties":{"name:sr":"11309 Лештане","opening_hours":"Mo-Fr 08:00-14:00; Sa 08:00-12:00; PH off","addr:housenumber":"60","name":"11309 Лештане","amenity":"post_office","phone":"+381 11 8030-790;+381 11 3210-156","ref":"11309","name:sr-Latn":"11309 Leštane","addr:pak":"153111","addr:street":"Маршала Тита"},"geometry":{"type":"Point","coordinates":[20.5755970520125,44.7309050684909]}},{"type":"Feature","properties":{"name:sr":"11351 Винча","opening_hours":"Mo-Fr 08:00-14:00; Sa 08:00-12:00; PH off","addr:housenumber":"172","name":"11351 Винча","amenity":"post_office","phone":"+381 11 3210-157","ref":"11351","name:sr-Latn":"11351 Vinča","addr:pak":"152208","addr:street":"Професора Васића"},"geometry":{"type":"Point","coordinates":[20.6152586693071,44.7572542592401]}}]}